README.md
setup.py
kolak/__init__.py
kolak/parser.py
kolak/util.py
kolak.egg-info/PKG-INFO
kolak.egg-info/SOURCES.txt
kolak.egg-info/dependency_links.txt
kolak.egg-info/requires.txt
kolak.egg-info/top_level.txt