Metadata-Version: 2.1
Name: kolak
Version: 0.1.5
Summary: universal rss parser
Home-page: https://gitlab.com/guangrei/Kolak
Author: guangrei
Author-email: myawn@pm.me
License: MIT
Keywords: rss feed parser podcast xml
